jderobotTypes/__init__.py
jderobotTypes/bumper.py
jderobotTypes/cmdvel.py
jderobotTypes/image.py
jderobotTypes/laserData.py
jderobotTypes/navdataData.py
jderobotTypes/pose3d.py
jderobotTypes/rgbd.py
jderobotTypes/sonar.py
jderobot_jderobottypes-1.0.0.dist-info/METADATA
jderobot_jderobottypes-1.0.0.dist-info/RECORD
jderobot_jderobottypes-1.0.0.dist-info/WHEEL
jderobot_jderobottypes-1.0.0.dist-info/top_level.txt
